import_name/__init__.py
import_name/main.py
import_name/run_main.py
import_name/fe/__init__.py
import_name/fe/fe.py
import_name/fe/fe2.py
import_name/model/__init__.py
import_name/model/model.py
import_name/utils/__init__.py
import_name/utils/utils.py
install_name-0.0.3.dist-info/METADATA
install_name-0.0.3.dist-info/WHEEL
install_name-0.0.3.dist-info/entry_points.txt
install_name-0.0.3.dist-info/top_level.txt
install_name-0.0.3.dist-info/RECORD
